dqt_serializers/__init__.py
dqt_serializers/base.py
dqt_serializers/csv_serializer.py
dqt_serializers/json_serializer.py
dqt_serializers-0.1.0.dist-info/METADATA
dqt_serializers-0.1.0.dist-info/WHEEL
dqt_serializers-0.1.0.dist-info/entry_points.txt
dqt_serializers-0.1.0.dist-info/top_level.txt
dqt_serializers-0.1.0.dist-info/RECORD
