Metadata-Version: 2.4
Name: dqt-serializers
Version: 0.1.0
Requires-Dist: pandas>=1.3.0
Requires-Dist: pyarrow>=5.0.0
Dynamic: requires-dist
